inspy_logger/__about__.py
inspy_logger/__init__.py
inspy_logger/common/__init__.py
inspy_logger/common/meta.py
inspy_logger/config/__init__.py
inspy_logger/config/dirs.py
inspy_logger/config/levels.py
inspy_logger/constants.py
inspy_logger/engine/__init__.py
inspy_logger/engine/__init__.py~
inspy_logger/engine/adapters/__init__.py
inspy_logger/engine/adapters/thread.py
inspy_logger/engine/errors.py
inspy_logger/engine/handlers.py
inspy_logger/errors/__init__.py
inspy_logger/helpers/__init__.py
inspy_logger/helpers/base_classes.py
inspy_logger/helpers/base_classes_old.py
inspy_logger/helpers/command_line/__init__.py
inspy_logger/helpers/debug/__init__.py
inspy_logger/helpers/debug/environment.py
inspy_logger/helpers/debug/system/__init__.py
inspy_logger/helpers/debug/system/processor/__init__.py
inspy_logger/helpers/debug/system/winx/__init__.py
inspy_logger/helpers/decorators.py
inspy_logger/helpers/descriptors.py
inspy_logger/helpers/network.py
inspy_logger/helpers/units.py
inspy_logger/manifest.py
inspy_logger/models/__init__.py
inspy_logger/models/announcement/__init__.py
inspy_logger/models/announcement/placeholder/__init__.py
inspy_logger/models/announcement/placeholder/helpers.py
inspy_logger/Scripts/main.py
inspy_logger/system/__init__.py
inspy_logger/system/linux.py
inspy_logger/system/mac_os.py
inspy_logger/system/win32.py
inspy_logger/tool/__init__.py
inspy_logger/tool/config/__init__.py
inspy_logger/tool/config/arguments/__init__.py
inspy_logger/types.py
inspy_logger/utils/__init__.py
inspy_logger/version/__init__.py
inspy_logger/version/VERSION.txt
inspy_logger/version.py
inspy_logger-3.2.3.dist-info/entry_points.txt
inspy_logger-3.2.3.dist-info/LICENSE.md
inspy_logger-3.2.3.dist-info/METADATA
inspy_logger-3.2.3.dist-info/WHEEL
inspy_logger-3.2.3.dist-info/RECORD
