Metadata-Version: 2.3
Name: inspy-logger
Version: 3.2.3
Summary: Colorable, scalable logger for CLI
License: MIT
Author: Taylor B.
Author-email: tayjaybabee@gmail.com
Requires-Python: >=3.10,<4.0
Classifier: License :: OSI Approved :: MIT License
Classifier: Programming Language :: Python :: 3
Classifier: Programming Language :: Python :: 3.10
Classifier: Programming Language :: Python :: 3.11
Classifier: Programming Language :: Python :: 3.12
Classifier: Programming Language :: Python :: 3.13
Requires-Dist: appdirs (>=1.4.4,<2.0.0)
Requires-Dist: packaging (>=24.1,<25.0)
Requires-Dist: platformdirs (>=4.2.2,<5.0.0)
Requires-Dist: psutil (>=6.0.0,<7.0.0)
Requires-Dist: pypattyrn (>=1.2,<2.0)
Requires-Dist: pyperclip (>=1.8.2,<2.0.0)
Requires-Dist: python-box (>=7.2.0,<8.0.0)
Requires-Dist: requests (>=2.32.3,<3.0.0)
Requires-Dist: rich (>=13.7.1,<14.0.0)
Requires-Dist: urllib3 (>1.26.5,<2)
